README.md
setup.py
fefu_admission/__init__.py
fefu_admission/cli.py
fefu_admission/prompt.py
fefu_admission/utils.py
fefu_admission.egg-info/PKG-INFO
fefu_admission.egg-info/SOURCES.txt
fefu_admission.egg-info/dependency_links.txt
fefu_admission.egg-info/entry_points.txt
fefu_admission.egg-info/requires.txt
fefu_admission.egg-info/top_level.txt
fefu_admission/fefu/__init__.py
fefu_admission/fefu/department.py
fefu_admission/fefu/settings.py
fefu_admission/fefu/university.py
fefu_admission/university/__init__.py
fefu_admission/university/enrollee.py
fefu_admission/university/type_of_completion.py
fefu_admission/university/applicants_holder/__init__.py
fefu_admission/university/applicants_holder/applicants_holder_base.py
fefu_admission/university/applicants_holder/printer.py
fefu_admission/university/department/__init__.py
fefu_admission/university/department/department.py
fefu_admission/university/department/serialization.py
fefu_admission/university/department/web_loader_thread.py
fefu_admission/university/university/__init__.py
fefu_admission/university/university/printer.py
fefu_admission/university/university/serialization.py
fefu_admission/university/university/university.py
fefu_admission/university/university/settings/__init__.py
fefu_admission/university/university/settings/serialization.py
fefu_admission/university/university/settings/settings.py