Metadata-Version: 2.1
Name: fefu-admission
Version: 1.9
Summary: UNKNOWN
Home-page: UNKNOWN
License: UNKNOWN
Platform: UNKNOWN
